README.rst
setup.py
djorm_core/__init__.py
djorm_core/models.py
djorm_core/utils.py
djorm_core/postgresql/__init__.py
djorm_ext_core.egg-info/PKG-INFO
djorm_ext_core.egg-info/SOURCES.txt
djorm_ext_core.egg-info/dependency_links.txt
djorm_ext_core.egg-info/not-zip-safe
djorm_ext_core.egg-info/top_level.txt